LICENSE.txt
README.md
setup.py
aiotoolbox/__init__.py
aiotoolbox/compat.py
aiotoolbox/context.py
aiotoolbox/defer.py
aiotoolbox/fork.py
aiotoolbox/func.py
aiotoolbox/iter.py
aiotoolbox/server.py
aiotoolbox/timer.py
aiotoolbox.egg-info/PKG-INFO
aiotoolbox.egg-info/SOURCES.txt
aiotoolbox.egg-info/dependency_links.txt
aiotoolbox.egg-info/requires.txt
aiotoolbox.egg-info/top_level.txt